fuzzycat/__init__.py
fuzzycat/__main__.py
fuzzycat/common.py
fuzzycat/config.py
fuzzycat/contrib.py
fuzzycat/data.py
fuzzycat/entities.py
fuzzycat/grobid_unstructured.py
fuzzycat/matching.py
fuzzycat/py.typed
fuzzycat/refs.py
fuzzycat/sandcrawler.py
fuzzycat/simple.py
fuzzycat/utils.py
fuzzycat/verify.py
fuzzycat-0.1.23.dist-info/LICENSE
fuzzycat-0.1.23.dist-info/METADATA
fuzzycat-0.1.23.dist-info/WHEEL
fuzzycat-0.1.23.dist-info/entry_points.txt
fuzzycat-0.1.23.dist-info/top_level.txt
fuzzycat-0.1.23.dist-info/RECORD
