Metadata-Version: 2.1
Name: fuzzycat
Version: 0.1.23
Summary: Fuzzy matching utilities for scholarly metadata
Home-page: https://github.com/miku/fuzzycat
Author: Martin Czygan
Author-email: martin@archive.org
License: UNKNOWN
Platform: UNKNOWN
Classifier: Programming Language :: Python :: 3
Classifier: License :: OSI Approved :: MIT License
Classifier: Operating System :: OS Independent
Requires-Python: >=3.6
Requires-Dist: dynaconf (>=3)
Requires-Dist: elasticsearch (<7.14.0,>=7.8.0)
Requires-Dist: elasticsearch-dsl (<8.0.0,>=7.0.0)
Requires-Dist: fatcat-openapi-client (>=0.4.0)
Requires-Dist: ftfy
Requires-Dist: glom
Requires-Dist: grobid-tei-xml (==0.1.*)
Requires-Dist: jellyfish
Requires-Dist: pyyaml
Requires-Dist: regex
Requires-Dist: requests (>=2)
Requires-Dist: thefuzz
Requires-Dist: toml
Requires-Dist: unidecode (>=0.10)
Requires-Dist: zstandard
Provides-Extra: dev
Requires-Dist: ipython ; extra == 'dev'
Requires-Dist: isort ; extra == 'dev'
Requires-Dist: mypy ; extra == 'dev'
Requires-Dist: pylint ; extra == 'dev'
Requires-Dist: pytest ; extra == 'dev'
Requires-Dist: pytest-cov ; extra == 'dev'
Requires-Dist: twine ; extra == 'dev'
Requires-Dist: yapf ; extra == 'dev'
